hubmigrate/__init__.py
hubmigrate/client.py
hubmigrate/classes/__init__.py
hubmigrate/classes/auth.py
hubmigrate/classes/migration.py
hubmigrate/classes/validation.py
hubmigrate/tests/__init__.py
hubmigrate/tests/get_data.py
hubmigrate-1.0.1.dist-info/METADATA
hubmigrate-1.0.1.dist-info/WHEEL
hubmigrate-1.0.1.dist-info/top_level.txt
hubmigrate-1.0.1.dist-info/RECORD
