Metadata-Version: 2.1
Name: hubmigrate
Version: 1.0.1
Summary: An open-source Python library is designed to simplify the process of migrating data to HubSpot, a powerful customer relationship management (CRM) platform. Whether you're moving contacts, companies, deals, or any other data to HubSpot, this library provides an easy-to-use interface for managing your migration tasks.
Author: bcostaaa01
Author-email: bcostaaa01@gmail.com
Requires-Dist: pytest
Requires-Dist: python-decouple
